Cy-SCM.py
MANIFEST.in
README
Readme.txt
epsc.iss
scm-0.7.win32.exe
setup.py
SCM.egg-info/PKG-INFO
SCM.egg-info/SOURCES.txt
SCM.egg-info/dependency_links.txt
SCM.egg-info/top_level.txt
epscApp/SCMPanel.py
epscApp/__init__.py
epscApp/aboutbox.py
epscApp/crystalDialog.py
epscApp/deformationPanel.py
epscApp/diffractionPanel.py
epscApp/epscController.py
epscApp/epscGui.py
epscApp/experimentPanel.py
epscApp/generalPanel.py
epscApp/hklDialog.py
epscApp/materialsNotebook.py
epscApp/optAlgorithmPanel.py
epscApp/optBCCDataPanel.py
epscApp/optFCCDataPanel.py
epscApp/optHCPDataPanel.py
epscApp/optNotebook.py
epscApp/phase1Panel.py
epscApp/plotNotebook.py
epscApp/plotPanel.py
epscApp/plotPanelErrMonitor.py
epscApp/plotPanelMacro.py
epscApp/plotPanelOverview.py
epscApp/plotPanelPhase1.py
epscApp/plotPanelSimulation.py
epscApp/plotPkg.py
epscApp/plotPkgErrMonitor.py
epscApp/processPanel.py
epscApp/reportPanel.py
epscApp/scmProject.py
epscApp/simulationPanel.py
epscApp/texturePanel.py
epscApp/treePanel.py
epscApp/welcomePanel.py
epscApp/epscComp/__init__.py
epscApp/epscComp/collectData.py
epscApp/epscComp/config.py
epscApp/epscComp/diffractionData.py
epscApp/epscComp/epscData.py
epscApp/epscComp/epscEngine.py
epscApp/epscComp/epscOptimizer.py
epscApp/epscComp/expData.py
epscApp/epscComp/extendedplotframe.py
epscApp/epscComp/generalData.py
epscApp/epscComp/interpolateFunction.py
epscApp/epscComp/matParameters.py
epscApp/epscComp/optData.py
epscApp/epscComp/optimize.py
epscApp/epscComp/parameter.py
epscApp/epscComp/plotEngine.py
epscApp/epscComp/processParameters.py
epscApp/epscComp/setParameters.py
epscApp/epscComp/superData.py
epscApp/epscComp/utility.py
epscApp/epscComp/epscCore/BCC.dif
epscApp/epscComp/epscCore/BCC.sx
epscApp/epscComp/epscCore/Beta_M5_BCC.dif
epscApp/epscComp/epscCore/DIFFRACTION_1.dif
epscApp/epscComp/epscCore/DIFFRACTION_1_HCP.dif
epscApp/epscComp/epscCore/DIFFRACTION_2.dif
epscApp/epscComp/epscCore/DIFFRACTION_FCC.dif
epscApp/epscComp/epscCore/EpscNP.exe
epscApp/epscComp/epscCore/EpscNp.for
epscApp/epscComp/epscCore/EpscNp_1phase.in
