Metadata-Version: 1.0
Name: SCM
Version: 1.0alpha
Summary: Gui for EPSC model and inverse analysis
Home-page: http://www.engdiff.org
Author: Ersan Ustundaq
Author-email: ustundaq@iastate.edu
License: UNKNOWN
Download-URL: http://engdiff.engineering.iastate.edu/packages/SCM-1.0alpha.linux-i686.tar.gz
Platform: UNKNOWN
